{
  "version": 2,
  "projects": [
    {
      "fieldConfig": {},
      "defaultName": "",
      "templates": [],
      "excludedNotes": [],
      "isDefault": false,
      "dataSource": {
        "kind": "folder",
        "config": {
          "path": "Projects - Demo Project",
          "recursive": false
        }
      },
      "newNotesFolder": "",
      "views": [
        {
          "config": {
            "fieldConfig": {
              "name": {
                "width": 360
              },
              "path": {
                "hide": true
              }
            }
          },
          "filter": {
            "conjunction": "and",
            "conditions": []
          },
          "colors": {
            "conditions": []
          },
          "sort": {
            "criteria": []
          },
          "name": "Table",
          "id": "d573718e-4ca6-4023-93be-ce518b180e4f",
          "type": "table"
        },
        {
          "config": {
            "groupByField": "status",
            "orderSyncField": "weight"
          },
          "filter": {
            "conjunction": "and",
            "conditions": []
          },
          "colors": {
            "conditions": []
          },
          "sort": {
            "criteria": []
          },
          "name": "Board",
          "id": "37e5b406-fb4d-4f0d-b8f1-a6521ffba285",
          "type": "board"
        },
        {
          "config": {
            "interval": "month",
            "dateField": "due",
            "checkField": "published"
          },
          "filter": {
            "conjunction": "and",
            "conditions": []
          },
          "colors": {
            "conditions": []
          },
          "sort": {
            "criteria": []
          },
          "name": "Calendar",
          "id": "9aafa2b7-b41b-4721-a6e2-b075372d92f7",
          "type": "calendar"
        },
        {
          "config": {
            "coverField": "image"
          },
          "filter": {
            "conjunction": "and",
            "conditions": []
          },
          "colors": {
            "conditions": []
          },
          "sort": {
            "criteria": []
          },
          "name": "Gallery",
          "id": "d4a2657c-ba34-4eaa-8d02-dfe44962daa3",
          "type": "gallery"
        }
      ],
      "name": "Demo project",
      "id": "accadd25-c2ca-47ae-9e73-b0fda80e7a4b",
      "path": "Projects - Demo Project"
    },
    {
      "fieldConfig": {},
      "defaultName": "",
      "templates": [],
      "excludedNotes": [],
      "isDefault": false,
      "dataSource": {
        "kind": "folder",
        "config": {
          "path": "",
          "recursive": true
        }
      },
      "newNotesFolder": "",
      "views": [
        {
          "config": {},
          "filter": {
            "conjunction": "and",
            "conditions": []
          },
          "colors": {
            "conditions": []
          },
          "sort": {
            "criteria": []
          },
          "id": "91c3e8ba-a040-4c28-87bc-9653acf2cde5",
          "name": "Table",
          "type": "table"
        }
      ],
      "id": "539fb6d2-42b9-4882-b271-6e18f1e5c3a1",
      "name": "Untitled project"
    }
  ],
  "archives": [],
  "preferences": {
    "projectSizeLimit": 1000,
    "frontmatter": {
      "quoteStrings": "PLAIN"
    },
    "locale": {
      "firstDayOfWeek": "default"
    },
    "commands": [],
    "linkBehavior": "open-editor"
  }
}